qat/__init__.so
qat/core/__init__.so
qat/core/application.so
qat/core/arg_parser.so
qat/core/assertion.so
qat/core/bits.so
qat/core/circuit_iterator.so
qat/core/connections.so
qat/core/console.so
qat/core/contexts.so
qat/core/distutils.so
qat/core/empty.so
qat/core/exceptions_utils.so
qat/core/formula_eval.so
qat/core/gate_set.so
qat/core/generator.so
qat/core/json.so
qat/core/junction.so
qat/core/loader.so
qat/core/optimizer.so
qat/core/parserconf.so
qat/core/plugins.so
qat/core/plugins_utils.so
qat/core/printer.so
qat/core/product.so
qat/core/qlmaas.so
qat/core/quameleon.so
qat/core/remap.so
qat/core/resourcemanager_access.so
qat/core/services.so
qat/core/simutil.so
qat/core/spins.so
qat/core/task.so
qat/core/util.so
qat/core/variables.so
qat/core/version.so
qat/core/circuit_builder/__init__.so
qat/core/circuit_builder/builder.so
qat/core/circuit_builder/circ_util.so
qat/core/circuit_builder/gate_dictionary.so
qat/core/circuit_builder/matrix_util.so
qat/core/formatter/result.so
qat/core/linking/__init__.so
qat/core/linking/util.so
qat/core/magic/__init__.so
qat/core/magic/install.so
qat/core/magic/magic.py
qat/core/magic/py_d3.py
qat/core/magic/js_scripts/FileSaver.js
qat/core/magic/js_scripts/custom.js
qat/core/magic/js_scripts/d3.min.js
qat/core/magic/js_scripts/display_library.js
qat/core/magic/js_scripts/svg-pan-zoom.js
qat/core/magic/svg/STIXMathJax_Main-Italic.otf
qat/core/magic/svg/__init__.so
qat/core/magic/svg/circ_to_svg.so
qat/core/magic/svg/display_gate.so
qat/core/qpu/__init__.so
qat/core/qpu/qpu.so
qat/core/static/css/__init__.so
qat/core/static/css/style.css
qat/core/static/html/__init__.so
qat/core/static/html/icon_svg.html
qat/core/wrappers/__init__.so
qat/core/wrappers/abstract_thrift_serializer.so
qat/core/wrappers/batch.so
qat/core/wrappers/circuit.so
qat/core/wrappers/hardware_specs.so
qat/core/wrappers/jax.so
qat/core/wrappers/job.so
qat/core/wrappers/number.so
qat/core/wrappers/observable.so
qat/core/wrappers/observable_util.so
qat_core-1.12.0.dist-info/licenses/LICENSE.txt
qat_core-1.12.0.dist-info/METADATA
qat_core-1.12.0.dist-info/WHEEL
qat_core-1.12.0.dist-info/top_level.txt
qat_core-1.12.0.dist-info/RECORD
