Metadata-Version: 2.4
Name: qat-core
Version: 1.12.0
Summary: Module qat-core [1ad243a] - Compiled by Eviden
Home-page: https://atos.net/en/lp/myqlm
Author: Eviden Quantum Lab
Author-email: myqlm@atos.net
License: Eviden myQLM EULA
Project-URL: Documentation, https://myqlm.github.io
Project-URL: Bug Tracker, https://github.com/myQLM/myqlm-issues/issues
Project-URL: Community, https://myqlmworkspace.slack.com
Keywords: Quantum,myQLM,QLM,Atos,Eviden
Platform: Operating System :: POSIX :: Linux
Classifier: Operating System :: POSIX :: Linux
Classifier: Programming Language :: Python :: 3.1
Classifier: Topic :: Scientific/Engineering
Classifier: License :: Other/Proprietary License
License-File: LICENSE.txt
Requires-Dist: thrift==0.21.0
Requires-Dist: numpy~=2.0
Requires-Dist: bitstring
Requires-Dist: wand
Requires-Dist: dill
Requires-Dist: matplotlib
Requires-Dist: Pillow
Requires-Dist: svgwrite
Requires-Dist: jax[cpu]
Requires-Dist: IPython
Requires-Dist: qat-comm
Dynamic: author
Dynamic: author-email
Dynamic: classifier
Dynamic: description
Dynamic: description-content-type
Dynamic: home-page
Dynamic: keywords
Dynamic: license
Dynamic: license-file
Dynamic: platform
Dynamic: project-url
Dynamic: requires-dist
Dynamic: summary
